volosti_common/__init__.py
volosti_common/common/__init__.py
volosti_common/common/schemas.py
volosti_common/person/__init__.py
volosti_common/person/dataclasses.py
volosti_common/person/queries.py
volosti_common/person/regexps.py
volosti_common/person/schemas.py
volosti_common/person/typedefs.py
volosti_common/py.typed
volosti_common-0.1.dev1.dist-info/LICENSE
volosti_common-0.1.dev1.dist-info/METADATA
volosti_common-0.1.dev1.dist-info/WHEEL
volosti_common-0.1.dev1.dist-info/RECORD
