Metadata-Version: 2.1
Name: volosti-common
Version: 0.1.dev1
Summary: Общий исходный код реализаций Волостей
Home-page: https://pypi.org/project/volosti-common
License: MIT
Author: Ruslan Ilyasovich Gilfanov
Author-email: ri.gilfanov@yandex.ru
Maintainer: Ruslan Ilyasovich Gilfanov
Maintainer-email: ri.gilfanov@yandex.ru
Requires-Python: >=3.9,<4.0
Classifier: Development Status :: 2 - Pre-Alpha
Classifier: License :: OSI Approved :: MIT License
Classifier: Programming Language :: Python
Classifier: Programming Language :: Python :: 3
Classifier: Programming Language :: Python :: 3.9
Classifier: Programming Language :: Python :: 3.10
Classifier: Programming Language :: Python :: 3.11
Classifier: Programming Language :: Python :: 3
Classifier: Programming Language :: Python :: 3.10
Classifier: Programming Language :: Python :: 3.11
Classifier: Programming Language :: Python :: 3.9
Classifier: Typing :: Typed
Provides-Extra: openssl
Provides-Extra: pycryptodome
Requires-Dist: argon2-cffi (>=21.3.0,<22.0.0)
Requires-Dist: babel (>=2.12.1,<3.0.0)
Requires-Dist: cryptography (>=39.0.2,<40.0.0) ; extra == "openssl"
Requires-Dist: httpx (>=0.23.3)
Requires-Dist: marshmallow (>=3.19.0,<4.0.0)
Requires-Dist: passlib (>=1.7.4,<2.0.0)
Requires-Dist: pycryptodome (>=3.17,<4.0) ; extra == "pycryptodome"
Project-URL: Repository, https://github.com/volosti/volosti-common
